pfm_search.py
setup.py
pfm_search.egg-info/PKG-INFO
pfm_search.egg-info/SOURCES.txt
pfm_search.egg-info/dependency_links.txt
pfm_search.egg-info/requires.txt
pfm_search.egg-info/top_level.txt