Metadata-Version: 2.2
Name: pfm-search
Version: 1.0.3
Summary: A Python module for fetching search results from PFM-Search
Author: Krushna
Author-email: your-email@example.com
Classifier: Programming Language :: Python :: 3
Classifier: License :: OSI Approved :: MIT License
Classifier: Operating System :: OS Independent
Requires-Dist: requests
Dynamic: author
Dynamic: author-email
Dynamic: classifier
Dynamic: requires-dist
Dynamic: summary
